[
  {
    "id": 1,
    "title": "Silent Night",
    "author": "Joseph Mohr",
    "lyric": [
      "Silent night, holy night",
      "All is calm, all is bright",
      "'Round yon virgin Mother and Child",
      "Holy infant so tender and mild",
      "Sleep in heavenly peace",
      "Sleep in heavenly peace",
      "Silent night, holy night!",
      "Shepherds quake at the sight!",
      "Glories stream from heaven afar;",
      "Heavenly hosts sing Al-le-lu-ia!",
      "Christ the Savior is born!",
      "Christ the Savior is born!",
      "Christ the Savior is born!",
      "Silent night, holy night",
      "Son of God, oh, love's pure light",
      "Radiant beams from Thy holy face",
      "With the dawn of redeeming grace",
      "Jesus, Lord at Thy birth",
      "Jesus, Lord at Thy birth",
      "Jesus, Lord at Thy birth"
    ]
  },
  {
    "id": 2,
    "title": "With You This Christmas",
    "author": "Why Don't We Just",
    "lyric": [
      "[Intro: Daniel Seavey]",
      "Hey Uh,",
      "hmm Hmm,",
      "hmm Oh-oh-oh",
      "[Verse 1: Zach Herron]",
      "Remember last December",
      "When we kissed under the mistletoe, oh, oh",
      "I let you wear my favorite sweater",
      "So you think of me when you're alone, yeah",
      "When we stay up talking way too much",
      "And we don't even need any coffee to keep us up, no",
      "Yeah, I know that I'm feeling something",
      "Right when I'm next to you, oh",
      "[Pre-Chorus: Jack Avery, Daniel Seavey]",
      "(Oh, oh-oh-oh)",
      "It's cold outside when I'm without you",
      "(Oh, oh-oh-oh)",
      "But you make me feel so warm",
      "[Chorus: Corbyn Besson, Daniel Seavey]",
      "(Ooh, ooh, ooh, yeah)",
      "Baby, can't you see",
      "Can't you see that I want you? (Ooh, ooh, yeah)",
      "Yeah, I just wanna be with you this Christmas",
      "[Post-Chorus: Daniel Seavey, Corbyn Besson]",
      "Mmm-mmhm...",
      "Mmm-mmm-mmh",
      "This Christmas",
      "Mmm-mmhm...",
      "Mmm-mmm-mmh",
      "This Christmas",
      "And to be honest, I can't live without you (No)",
      "Just ask my friends, they say I'm so about you",
      "Buy you anything you want (Hey), Gucci and Saint Laurent (Yeah)",
      "Girl, you know what I'm up, I'm just saying",
      "Santa gon' be leaving at 5 AM",
      "Baby, I can pull up, it don't matter what time it is",
      "Yeah, I know, it's Christmas Eve",
      "But, girl, you're all I need",
      "I'll be there in one, two, three",
      "Yeah, anything if I can get to you",
      "[Chorus: Corbyn Besson & Daniel Seavey]",
      "(Ooh, ooh, ooh, yeah)",
      "Baby, can't you see",
      "Can't you see that I want you? (Ooh, ooh, yeah)",
      "Yeah, I just wanna be with you this Christmas",
      "[Post-Chorus: Daniel Seavey, Corbyn Besson]",
      "Mmm-mmhm... (Ooh)",
      "Mmm-mmm-mmh",
      "This Christmas",
      "Mmm-mmhm... (Oh oh-woah)",
      "Mmm-mmm-mmh",
      "This Christmas",
      "[Outro: Daniel Seavey, Corbyn Besson]",
      "Yeah yeah",
      "Mmm-mmm-mmh",
      "This Christmas",
      "Mmm-mmhm...",
      "Mmm-mmm-mmh",
      "This Christmas"
    ]
  },
  {
    "title": "The little drummer boy",
    "author": "Harry Simeone",
    "lyric": [
      "Come, they told me pa-rum pum pum pum",
      "Our newborn King to see, pa-rum pum pum pum",
      "Our finest gifts we bring pa-rum pum pum pum",
      "To lay before the King pa-rum pum pum pum",
      "Rum pum pum pum, rum pum pum pum",
      "So to honor Him pa-rum pum pum pum",
      "When we come",
      "Baby Jesus, pa-rum pum pum pum",
      "I am a poor boy too, pa-rum pum pum pum",
      "I have no gift to bring pa-rum pum pum pum",
      "That's fit to give our King pa- rum pum pum pum",
      "Rum pum pum pum, rum pum pum pum",
      "Shall I play for you, pa-rum pum pum pum",
      "On my drum?",
      "Mary nodded pa-rum pum pum pum",
      "The Ox and Lamb kept time pa-rum pum pum pum",
      "I played my drum for Him pa-rum pum pum pum",
      "I played my best for Him pa -rum pum pum pum",
      "Rum pum pum pum, rum pum pum pum",
      "Then He smiled at me pa-rum pum pum pum",
      "Me and my drum",
      "Me and my drum"
    ]
  },
  {
    "id": 3,
    "title": "O Little Town Of Bethlehem",
    "author": "Philips Brooks",
    "lyric": [
      "Oh little town of Bethlehem, how still we see thee lie",
      "Above thy deep and dreamless sleep the silent stars go by",
      "Yet in thy dark streets shineth, the everlasting light",
      "The hopes and fears of all the years are met in thee tonight.",
      "For Christ is born of Mary, and gathered all above",
      "While mortals sleep the angels keep their watch of wondering love",
      "Oh morning stars together, proclaim thy holy birth.",
      "And praises sing to God the king, and peace to men on earth.",
      "Oh little town of Bethlehem, how still we see thee lie",
      "Above thy deep and dreamless sleep the silent stars go by",
      "Yet in thy dark streets shineth, the everlasting light",
      "The hopes and fears of all the years are met in thee tonight."
    ]
  },
  {
    "id": 4,
    "title": "Angels,from the realms of Glory ",
    "author": " James Montgomery",
    "lyric": [
      "Angels from the realms of glory,",
      "Wing your flight o'er all the earth;",
      "Ye who sang creation's story,",
      "Now proclaim Messiah's birth",
      "Come and worship,",
      "Come and worship,",
      "Worship Christ, the newborn King!",
      "Shepherds, in the fields abiding",
      "Watching o'er your flocks by night",
      "God with man is now residing",
      "Yonder shines the infant Light",
      "Come and worship",
      "Come and worship",
      "Worship Christ, the newborn King!",
      "Sages, leave your contemplations",
      "Brighter visions beam afar",
      "Seek the great desire of nations",
      "Ye have seen His natal star",
      "Come and worship",
      "Come and worship",
      "Worship Christ, the newborn King!",
      "Saints before the altar bending",
      "Watching long in hope and fear",
      "Suddenly the Lord, descending",
      "In His temple shall appear",
      "Come and worship",
      "Come and worship",
      "Worship Christ, the newborn King!"
    ]
  },
  {
    "id": 5,
    "title": " I Heard the Bells on Christmas Day",
    "author": " Henry Wadsworth Longfellow ",
    "lyric": [
      "I heard the bells on Christmas day",
      "Their old familiar carols play",
      "And mild and sweet their songs repeat",
      "Of peace on earth good will to men",
      "And the bells are ringing (peace on earth)",
      "Like a choir they're singing (peace on earth)",
      "In my heart I hear them (peace on earth)",
      "Peace on earth, good will to men",
      "And in despair I bowed my head",
      "There is no peace on earth I said",
      "For hate is strong and mocks the song",
      "Of peace on earth, good will to men",
      "But the bells are ringing (peace on earth)",
      "Like a choir singing (peace on earth)",
      "Does anybody hear them? (peace on earth)",
      "Peace on earth, good will to men",
      "Then rang the bells more loud and deep",
      "God is not dead, nor does he sleep (peace on earth, peace on earth)",
      "The wrong shall fail, the right prevail",
      "With peace on earth, good will to men",
      "Then ringing singing on its way",
      "The world revolved from night to day",
      "A voice, a chime, a chant sublime",
      "Of peace on earth, good will to men",
      "And the bells they're ringing (peace on earth)",
      "Like a choir they're singing (peace on earth)",
      "And with our hearts we'll hear them (peace on earth)",
      "Peace on earth, good will to men",
      "Do you hear the bells they're ringing? (peace on earth)",
      "The life the angels singing (peace on earth)",
      "Open up your heart and hear them (peace on earth)",
      "Peace on earth, good will to men",
      "Peace on earth, peace on earth",
      "Peace on earth, Good will to men"
    ]
  },
  {
    "id": 6,
    "title": "Go Tell It on the Mountain",
    "author": "John Wesley Work",
    "lyric": [
      "Go tell it on the mountain",
      "Over the hills and everywhere",
      "Go tell it on the mountain",
      "Our Jesus Christ is born",
      "When I was a seeker",
      "I sought both night and day",
      "I asked the Lord to help me",
      "And he showed me the way",
      "Go tell it on the mountain",
      "Over the hills and everywhere",
      "Go tell it on the mountain",
      "Our Jesus Christ is born",
      "He made me a watchman",
      "Upon a city wall",
      "And if I am a Christian",
      "I am the least of all",
      "Go tell it on the mountain",
      "Over the hills and everywhere",
      "Go tell it on the mountain",
      "Our Jesus Christ is born"
    ]
  },
  {
    "id": 7,
    "title": "What Child is This?",
    "author": "William Chatterton Dix",
    "lyric": [
      "What child is this",
      " Who's laid to rest",
      "On Mary's lap is Sleeping?",
      "Whom angels greet with anthems sweet",
      " While shepherd's watch are keeping",
      "This this is Christ the King",
      "Whom shepherds guard and angels sing",
      "Haste! haste!",
      " To bring him, Lord!",
      "The babe, the son of Mary",
      "Why lies He in such mean estate",
      "Where ox and ass are feeding?",
      "Good Christians, fear, for sinners here",
      "The silent Word is pleading",
      "Nails, spear shall pierce Him through",
      "The cross be borne for me, for you",
      " Hail, hail the Word made flesh",
      "The Babe, the Son of Mary",
      "So bring Him incense, gold and myrrh",
      "Come peasant, king to own Him",
      "The King of kings salvation brings",
      "Let loving heart enthrone Him",
      "Raise, raise a song on high",
      "The virgin sings her lullaby",
      " Joy, joy for Christ is born",
      "The Babe, the Son of Mary"
    ]
  },
  {
    "id": 8,
    "title": "joy to the world",
    "author": "Isaac Watts",
    "lyric": [
      "Joy to the world!",
      "Joy to the world! Oh, woah",
      "Joy to the world! The Lord is come",
      "Let earth receive her King!",
      "Let every heart prepare Him room",
      "And heaven and nature sing",
      "And heaven and nature sing",
      "And heaven, and heaven and nature sing",
      "Joy to the world!",
      "Joy to the world! Oh",
      "Joy to the world! The Savior reigns",
      "Let men their songs employ",
      "While fields and floods",
      "Rocks, hills and plains",
      "Repeat the sounding joy",
      "Repeat the sounding joy",
      "Repeat, repeat the sounding joy",
      "Joy to the world then we sing",
      "Let the earth receive her King!",
      "Joy to the world then we sing",
      "Let the angel voices ring",
      "Joy to the world then we sing",
      "Let the men their songs employ",
      "Joy to the world then we sing",
      "And repeat the sounding joy",
      "He rules the world with truth and grace",
      "And makes the…"
    ]
    

  },
  {
    "id": 9,
    "title": "O Holy Night",
    "author": "Placide Cappeau",
    "lyric": [
      "Oh holy night",
      "The stars are brightly shining",
      "It is the night of our dear savior's birth",
      "Long lay the world in sin and error, pining",
      "'Til He appeared and the soul felt it's worth",
      "A thrill of hope, the weary world rejoices",
      "For yonder breaks a new and glorious morn'",
      "Fall on your knees, oh, hear the Angels' voices",
      "Oh, night divine, oh, night when Christ was born",
      "Oh, night divine, oh, night, oh night divine",
      "A thrill of hope, the weary world rejoices",
      "For yonder breaks a new and glorious morn'",
      "Fall on your knees, oh, hear, hear the Angels' voices",
      "Oh, night divine, yeah, oh, night when Christ was born",
      "Oh, night divine, oh, night, oh night divine",
      "Oh yes, said rise (oh night divine)",
      "It is the night of the Lord…"      
    ]
    
          
  },
  {
    "id": 10,
    "title": "we wish you a merry christmas",
    "author": "Arthur Warrell",
    "lyric": [
      "We wish you a merry Christmas and a happy new year",
      "We wish you a merry Christmas",
      "We wish you a merry Christmas",
      "Good tidings we bring to you and your kin",
      "We wish you a merry Christmas and a happy new year",
      "Oh, bring us some figgy pudding",
      "Oh, bring us some figgy pudding",
      "Oh, bring us some figgy pudding",
      "And bring it right here",
      "Good tidings we bring to you and your kin",
      "We wish you a merry Christmas and a happy new year",
      "We won't go until we get some",
      "We won't go until we get some",
      "We won't go until we get some",
      "So bring it right here",
      "Good tidings we bring to you and your kin",
      "We wish you a merry Christmas and a happy new year",
      "We all like our figgy pudding",
      "We all…"
    ]
    
  },
  {
    "id": 11,
    "title": "do you hear what i hear",
    "author": "Noel Regney",
    "lyric": [
      "Said the night wind to the little lamb",
      "Do you see what I see",
      "Way up in the sky little lamb",
      "Do you see what I see",
      "A star, a star",
      "Dancing in the night",
      "With a tail as big as a kite",
      "With a tail as big as a kite",
      "Said the little lamb to the shepherd boy",
      "Do you hear what I hear",
      "(Do you hear what I hear)",
      "Ringing through the sky shepherd boy",
      "Do you hear what I hear",
      "(Do you hear what I hear)",
      "A song, a song",
      "High above the trees",
      "With a voice as big as the sea",
      "With a voice as big as the sea",
      "Said the shepherd boy to the mighty king",
      "Do you know what I know",
      "In your palace wall mighty king",
      "Do you know what I know",
      "(Do you know what I know)",
      "A child, a child",
      "Shivers in the cold",
      "Let us bring him silver and gold",
      "Let us bring him silver and…"
    ]
    
  },
  {
    "id": 12,
    "title": "deck the halls",
    "author": "Thomas Oliphant",
    "lyric": [
      "Fa la la la la, la la la la",
      "Fa la la la la, la la la la",
      "Oh no no",
      "Deck the halls with boughs of holly",
      "Fa la la la la, la la la la (fa la la la la, la la la la)",
      "'Tis the season to be jolly",
      "Fa la la la la, la la la la (fa la la la la, la la la la)",
      "Don we now our gay apparel",
      "Fa la la la la, la la la la (fa la la la la, la la la la)",
      "Troll the ancient Yuletide carol",
      "Fa la la la la, la la la la",
      "Fa la la la la, la la la la la la",
      "Fa la la la la, fa la la la",
      "Fa la la la la, la la la la la la",
      "Fa la la la la, fa la la la",
      "See the blazing yule before us",
      "Fa la la la la, la la la la (fa la la la la, la la la la)",
      "Strike the harp and join the chorus",
      "(Fa la la la la, la la la, fa la la la la, la la la)",
      "Follow me in merry measure",
      "Fa la la la la, la la la la, fa la la la la, la la…"
    ]
    
  },
  {
    "id": 13,
    "title": "chipmunk christmas song",
    "author": "Ross Bagdasarian",
    "lyric": [
      "Alright you Chipmunks",
      "Ready to sing your song?",
      "I'll say we are",
      "Yeah, let's sing it now!",
      "Okay, Simon?",
      "Okay",
      "Okay, Theodore?",
      "Okay",
      "Okay, Alvin? Alvin? Alvin!",
      "Christmas, Christmas time is near",
      "Time for toys and time for cheer",
      "We've been good, but we can't last",
      "Hurry Christmas, hurry fast",
      "Want a plane that loops the loop",
      "Me, I want a hula hoop",
      "We can hardly stand the wait",
      "Please Christmas, don't be late",
      "Okay, fellas get ready",
      "That was very good, Simon",
      "Naturally!",
      "Very good, Theodore",
      "He-he-he-he",
      "Ah-Alvin, you were a little flat",
      "Watch it, ah-Alvin... Alvin? Alvin!",
      "Okay",
      "Want a plane that loops the loop",
      "I still want a hula hoop",
      "We can hardly stand the wait",
      "Please Christmas, don't be late",
      "We can hardly stand the wait",
      "Please Christmas, don't be late",
      "Very…"
    ]
    
  },
  {
    "id": 14,
    "title": "have a jolly christmas",
    "author": "Burl Ives",
    "lyric": [
      "Have a holly jolly Christmas",
      "It's the best time of the year",
      "Now I don't know if there'll be snow",
      "But have a cup of cheer",
      "Have a holly jolly Christmas",
      "And when you walk down the street",
      "Say hello to friends you know",
      "And everyone you meet",
      "Ho ho the mistletoe",
      "Is hung where you can see",
      "Somebody waits for you",
      "Kiss her once for me",
      "Have a holly jolly Christmas",
      "And in case you didn't hear",
      "Oh by golly have a holly jolly Christmas",
      "This year",
      "Ho ho…"
    ]
    
  },
  {
    "id": 16,
    "title": "let it snow",
    "author": "John Green",
    "lyric": [
      "Oh, the weather outside is frightful",
"But the fire is so delightful",
"And since we've no place to go",
"Let it snow, let it snow, let it snow",
"Man it doesn't show signs of stoppin'",
"And I brought me some corn for poppin'",
"The lights are turned way down low",
"Let it snow, let it snow, let it snow",
"When we finally kiss good-night",
"How I'll hate going out in the storm",
"But if you really hold me tight",
"All the way home I'll be warm",
"And the fire is slowly dying",
"And, my dear, we're still good-bye-ing",
"But as long as you'd love me so",
"Let it snow, let it snow, and snow",
"When we finally kiss…"
    ]
    
  }
]